README.md
setup.py
cancergenomeinterpreter/__init__.py
cancergenomeinterpreter/main.py
cancergenomeinterpreter.egg-info/PKG-INFO
cancergenomeinterpreter.egg-info/SOURCES.txt
cancergenomeinterpreter.egg-info/dependency_links.txt
cancergenomeinterpreter.egg-info/entry_points.txt
cancergenomeinterpreter.egg-info/requires.txt
cancergenomeinterpreter.egg-info/top_level.txt
cancergenomeinterpreter/cna/__init__.py
cancergenomeinterpreter/cna/main.py
cancergenomeinterpreter/cna/modules/__init__.py
cancergenomeinterpreter/cna/modules/driver_statement.py
cancergenomeinterpreter/cna/modules/input_preprocessing.py
cancergenomeinterpreter/cna/modules/output_format.py
cancergenomeinterpreter/fus/__init__.py
cancergenomeinterpreter/fus/main.py
cancergenomeinterpreter/fus/modules/__init__.py
cancergenomeinterpreter/fus/modules/driver_statement.py
cancergenomeinterpreter/fus/modules/input_preprocessing.py
cancergenomeinterpreter/fus/modules/output_format.py
cancergenomeinterpreter/mut/__init__.py
cancergenomeinterpreter/mut/main.py
cancergenomeinterpreter/mut/modules/__init__.py
cancergenomeinterpreter/mut/modules/call_fiscore.py
cancergenomeinterpreter/mut/modules/dna_mutation_annotation.py
cancergenomeinterpreter/mut/modules/driver_prediction.py
cancergenomeinterpreter/mut/modules/driver_rules.py
cancergenomeinterpreter/mut/modules/input_preprocessing.py
cancergenomeinterpreter/mut/modules/lib.py
cancergenomeinterpreter/mut/modules/match_metadata.py
cancergenomeinterpreter/mut/modules/output_format.py
cancergenomeinterpreter/mut/utils/__init__.py
cancergenomeinterpreter/mut/utils/constants.py
cancergenomeinterpreter/mut/utils/faidx.py
cancergenomeinterpreter/mut/utils/progress.py
cancergenomeinterpreter/prescription/__init__.py
cancergenomeinterpreter/prescription/main.py
cancergenomeinterpreter/prescription/entities/__init__.py
cancergenomeinterpreter/prescription/entities/alteration.py
cancergenomeinterpreter/prescription/entities/bioactivity.py
cancergenomeinterpreter/prescription/entities/biomarker.py
cancergenomeinterpreter/prescription/entities/genemarks.py
cancergenomeinterpreter/prescription/entities/tumor.py
cancergenomeinterpreter/utils/__init__.py
cancergenomeinterpreter/utils/constants.py
cancergenomeinterpreter/utils/lib.py
