Metadata-Version: 1.0
Name: cancergenomeinterpreter
Version: 1.0.1
Summary: Cancer Genome Interpreter
Home-page: https://bitbucket.org/bbglab/cancergenomeinterpreter
Author: BBGLab - Barcelona Biomedical Genomics Group
Author-email: bbglab@irbbarcelona.org
License: Apache 2.0
Platform: UNKNOWN
